chalk/__init__.py
chalk/align.py
chalk/arrow.py
chalk/combinators.py
chalk/core.py
chalk/envelope.py
chalk/model.py
chalk/monoid.py
chalk/py.typed
chalk/style.py
chalk/subdiagram.py
chalk/trace.py
chalk/trail.py
chalk/transform.py
chalk/types.py
chalk/utils.py
chalk/visitor.py
chalk/backend/__init__.py
chalk/backend/cairo.py
chalk/backend/svg.py
chalk/backend/tikz.py
chalk/shapes/__init__.py
chalk/shapes/arc.py
chalk/shapes/arrowheads.py
chalk/shapes/image.py
chalk/shapes/latex.py
chalk/shapes/path.py
chalk/shapes/segment.py
chalk/shapes/shape.py
chalk/shapes/text.py
chalk_diagrams-0.2.2.dist-info/LICENSE
chalk_diagrams-0.2.2.dist-info/METADATA
chalk_diagrams-0.2.2.dist-info/WHEEL
chalk_diagrams-0.2.2.dist-info/top_level.txt
chalk_diagrams-0.2.2.dist-info/RECORD
