Metadata-Version: 2.1
Name: chalk-diagrams
Version: 0.2.2
Summary: A declarative drawing API
Home-page: https://github.com/chalk-diagrams/chalk
Author: Dan Oneață
Author-email: dan.oneata@gmail.com
License: MIT
Project-URL: Documentation, https://chalk-diagrams.github.io
Project-URL: Source Code, https://github.com/chalk-diagrams/chalk
Project-URL: Issue Tracker, https://github.com/chalk-diagrams/chalk/issues
Classifier: Intended Audience :: Science/Research
Classifier: Operating System :: OS Independent
Classifier: Programming Language :: Python :: 3
Classifier: Programming Language :: Python :: 3.7
Classifier: Programming Language :: Python :: 3.8
Classifier: Programming Language :: Python :: 3.9
Classifier: License :: OSI Approved :: MIT License
Classifier: Topic :: Scientific/Engineering
License-File: LICENSE
Requires-Dist: toolz
Requires-Dist: colour
Requires-Dist: svgwrite
Requires-Dist: Pillow
Requires-Dist: loguru
Requires-Dist: chalk-planar
Requires-Dist: typing-extensions
Requires-Dist: importlib-metadata
Provides-Extra: latex
Requires-Dist: latextools ; extra == 'latex'
Provides-Extra: png
Requires-Dist: pycairo ; extra == 'png'
Provides-Extra: svg
Requires-Dist: cairosvg ; extra == 'svg'
Provides-Extra: tikz
Requires-Dist: pylatex ; extra == 'tikz'
